dnsurlsearch/DNSurlSearch.py
dnsurlsearch/Found_url.txt
dnsurlsearch/StatsDomain
dnsurlsearch/TODO.txt
dnsurlsearch/__about__.py
dnsurlsearch/__init__.py
dnsurlsearch/blacklistbis
dnsurlsearch/main.py
dnsurlsearch/named_dump.db
dnsurlsearch/testApi.py
dnsurlsearch/whitelistbis
dnsurlsearch-0.0.9.dist-info/METADATA
dnsurlsearch-0.0.9.dist-info/WHEEL
dnsurlsearch-0.0.9.dist-info/licenses/LICENSE.txt
dnsurlsearch-0.0.9.dist-info/RECORD
