Metadata-Version: 2.1
Name: dnsurlsearch
Version: 0.0.9
Project-URL: Documentation, https://github.com/Nicola-31/dnsurlsearch#readme
Project-URL: Issues, https://github.com/Nicola-31/dnsurlsearch/issues
Project-URL: Source, https://github.com/Nicola-31/dnsurlsearch
Author-email: Nicolas Jeudy <nicola.jeudy@gmail.com>
License-Expression: MIT
License-File: LICENSE.txt
Keywords: PiHole,bind9,dns,dns protocol,sniffer,tcpdump,url
Classifier: Development Status :: 4 - Beta
Classifier: Programming Language :: Python
Classifier: Programming Language :: Python :: Implementation :: CPython
Classifier: Programming Language :: Python :: Implementation :: PyPy
Requires-Python: >=3
